streamlit_raster/__init__.py
streamlit_raster/streamlit_raster.py
streamlit_raster-0.2.0.dist-info/LICENSE
streamlit_raster-0.2.0.dist-info/METADATA
streamlit_raster-0.2.0.dist-info/WHEEL
streamlit_raster-0.2.0.dist-info/dependency_links.txt
streamlit_raster-0.2.0.dist-info/top_level.txt
streamlit_raster-0.2.0.dist-info/RECORD
